sc2ladderMgmt/__init__.py
sc2ladderMgmt/__main__.py
sc2ladderMgmt/__version__.py
sc2ladderMgmt/cli.py
sc2ladderMgmt/constants.py
sc2ladderMgmt/functions.py
sc2ladderMgmt/ladders.py
sc2ladderMgmt/dataLadder/ladder_localhost.json
sc2ladderMgmt/dataLadder/ladder_testinvalid.json
sc2ladderMgmt/dataLadder/ladder_versentiedge.json
sc2ladderMgmt-0.1.5.dist-info/METADATA
sc2ladderMgmt-0.1.5.dist-info/RECORD
sc2ladderMgmt-0.1.5.dist-info/WHEEL
sc2ladderMgmt-0.1.5.dist-info/entry_points.txt
sc2ladderMgmt-0.1.5.dist-info/top_level.txt
