Metadata-Version: 2.1
Name: sc2ladderMgmt
Version: 0.1.5
Summary: A system for managing ladder profiles for AI, bot and human Starcraft 2 matches.
Home-page: https://github.com/ttinies/sc2ladderMgmt
Author: Versentiedge LLC
Author-email: help.fool@versentiedge.com
License: Apache License 2.0
Platform: UNKNOWN
Classifier: License :: OSI Approved :: Apache Software License
Classifier: Programming Language :: Python
Classifier: Programming Language :: Python :: 3
Classifier: Programming Language :: Python :: 3.6
Classifier: Programming Language :: Python :: Implementation :: CPython
Classifier: Programming Language :: Python :: Implementation :: PyPy
Classifier: Topic :: Games/Entertainment :: Real Time Strategy
Classifier: Topic :: Scientific/Engineering :: Artificial Intelligence
Requires-Python: >2.6
